threatrack_iocextract/__init__.py
threatrack_iocextract/iocextract.py
threatrack_iocextract/patterns/defangs.csv
threatrack_iocextract/patterns/hostname_whitelist.csv
threatrack_iocextract/patterns/patterns.csv
threatrack_iocextract/patterns/schemes.csv
threatrack_iocextract/patterns/tlds.csv
threatrack_iocextract-0.0.9.dist-info/METADATA
threatrack_iocextract-0.0.9.dist-info/RECORD
threatrack_iocextract-0.0.9.dist-info/WHEEL
threatrack_iocextract-0.0.9.dist-info/top_level.txt
