Metadata-Version: 2.1
Name: threatrack-iocextract
Version: 0.0.9
Summary: IOC extractor
Home-page: https://github.com/threatrack/threatrack_iocextract
Author: 
Author-email: 
License: UNKNOWN
Platform: UNKNOWN
Classifier: Programming Language :: Python
Classifier: License :: OSI Approved :: MIT License
Classifier: Operating System :: OS Independent
